{"DATUM":"02 04 2001\nПринят ведущим инженером временно сроком на два месяца в связи с разработкой документов на проведение тактико-специальных учений\nШтаб по делам гражданской обороны и чрезвычайным ситуациям\nВолгоградское открытое акционерное общество \"Химпром\"\nПриказ №270к от 02.04.2001г\n\n","GUEST_DATE":"<1962-03-24>","GUEST_NAME":"mamapa","HOST_DATE":"<2001-04-02>","HOST_NAME":"mamapa","PATH":"assets/20200910-ma/8974-8991.pdf","PRIVACY":"public","UUID":"A57FAB99-DAED-4744-9FE4-96574CB6951A"}